[{"__symbolic":"module","version":4,"metadata":{"UserState":{"__symbolic":"interface"},"UserReducers":{"user":{"__symbolic":"reference","module":"../dashboard/user.reducer","name":"userReducer","line":45,"character":7},"resetPasswordRequest":{"__symbolic":"reference","module":"../reset-password/reset-password-request.reducer","name":"reducer","line":46,"character":23},"changePassword":{"__symbolic":"reference","module":"../change-password/change-password.reducer","name":"reducer","line":47,"character":17},"searchView":{"__symbolic":"reference","module":"../search-account/search.reducer","name":"reducer","line":48,"character":13},"editProfile":{"__symbolic":"reference","module":"../profile-edit/edit-profile.reducer","name":"reducer","line":49,"character":14}},"FeatureState":{"__symbolic":"interface"},"selectFeatureState":{"__symbolic":"call","expression":{"__symbolic":"reference","module":"@ngrx/store","name":"createFeatureSelector","line":58,"character":34},"arguments":["user"]},"getUserInforamtionStatus":{"__symbolic":"call","expression":{"__symbolic":"reference","module":"@ngrx/store","name":"createSelector","line":60,"character":40},"arguments":[{"__symbolic":"reference","name":"selectFeatureState"},{"__symbolic":"error","message":"Lambda not supported","line":60,"character":75}]},"isSignedIn":{"__symbolic":"call","expression":{"__symbolic":"reference","module":"@ngrx/store","name":"createSelector","line":61,"character":26},"arguments":[{"__symbolic":"reference","name":"selectFeatureState"},{"__symbolic":"error","message":"Lambda not supported","line":61,"character":61}]},"selectResetPasswordRequestState":{"__symbolic":"call","expression":{"__symbolic":"reference","module":"@ngrx/store","name":"createSelector","line":63,"character":47},"arguments":[{"__symbolic":"reference","name":"selectFeatureState"},{"__symbolic":"error","message":"Lambda not supported","line":65,"character":1}]},"getNumberOfRequeseted":{"__symbolic":"call","expression":{"__symbolic":"reference","module":"@ngrx/store","name":"createSelector","line":67,"character":37},"arguments":[{"__symbolic":"reference","name":"selectResetPasswordRequestState"},{"__symbolic":"reference","module":"../reset-password/reset-password-request.reducer","name":"getNumberOfRequeseted","line":69,"character":1}]},"getResetPasswordRequestStatus":{"__symbolic":"call","expression":{"__symbolic":"reference","module":"@ngrx/store","name":"createSelector","line":71,"character":45},"arguments":[{"__symbolic":"reference","name":"selectResetPasswordRequestState"},{"__symbolic":"reference","module":"../reset-password/reset-password-request.reducer","name":"getStatus","line":73,"character":1}]},"selectUserInformaionState":{"__symbolic":"call","expression":{"__symbolic":"reference","module":"@ngrx/store","name":"createSelector","line":77,"character":41},"arguments":[{"__symbolic":"reference","name":"selectFeatureState"},{"__symbolic":"error","message":"Lambda not supported","line":77,"character":76}]},"getUser":{"__symbolic":"call","expression":{"__symbolic":"reference","module":"@ngrx/store","name":"createSelector","line":78,"character":23},"arguments":[{"__symbolic":"reference","name":"selectUserInformaionState"},{"__symbolic":"reference","module":"../dashboard/user.reducer","name":"getUser","line":78,"character":65}]},"selectSearchState":{"__symbolic":"call","expression":{"__symbolic":"reference","module":"@ngrx/store","name":"createSelector","line":82,"character":33},"arguments":[{"__symbolic":"reference","name":"selectFeatureState"},{"__symbolic":"error","message":"Lambda not supported","line":82,"character":68}]},"getSearchStatus":{"__symbolic":"call","expression":{"__symbolic":"reference","module":"@ngrx/store","name":"createSelector","line":83,"character":31},"arguments":[{"__symbolic":"reference","name":"selectSearchState"},{"__symbolic":"reference","module":"../search-account/search.reducer","name":"getStatus","line":83,"character":65}]},"getUserInfo":{"__symbolic":"call","expression":{"__symbolic":"reference","module":"@ngrx/store","name":"createSelector","line":84,"character":27},"arguments":[{"__symbolic":"reference","name":"selectSearchState"},{"__symbolic":"reference","module":"../search-account/search.reducer","name":"getUserInfo","line":84,"character":61}]}}}]